README.md
setup.py
nmfia/__init__.py
nmfia.egg-info/PKG-INFO
nmfia.egg-info/SOURCES.txt
nmfia.egg-info/dependency_links.txt
nmfia.egg-info/top_level.txt
nmfia/calc/__init__.py
nmfia/calc/cvt_bond.py
nmfia/client/__init__.py
nmfia/client/connect.py
nmfia/client/request.py