Metadata-Version: 1.2
Name: nmfia
Version: 0.0.2
Summary: 9M Technologies Fixed Income Analysis
Home-page: https://github.com/9m-tec/nmfia
Author: 9M Technologies
License: UNKNOWN
Platform: any
Requires-Python: >=3.6.7
